{
  "green-3-20km_ent_fea_1ws_np4": {
    "Albany cuda compiler": "Cuda 112",
    "Albany cxx compiler": "GNU 8.3.1",
    "Albany git branch": "master",
    "Albany git commit id": "c6a2c71",
    "Simulation start time": "02:44:22",
    "Trilinos git commit id": "33fab62",
    "case": "green-3-20km_ent_fea_1ws",
    "date": 20230227,
    "max host memory": 3112.375,
    "max kokkos memory": 5996.01,
    "np": 4,
    "passed": true,
    "timers": {
      "Albany Fill: Jacobian:": 19.0327,
      "Albany Fill: Residual:": 15.9327,
      "Albany Jacobian Fill: Evaluate:": 15.7865,
      "Albany Jacobian Fill: Export:": 0.253786,
      "Albany Residual Fill: Evaluate:": 15.5906,
      "Albany Residual Fill: Export:": 0.0702696,
      "Albany Total Time:": 41.9905,
      "Albany: Setup Time:": 5.80764,
      "Albany: Total Fill Time:": 34.9681,
      "NOX Total Linear Solve:": 0.8366,
      "NOX Total Preconditioner Construction:": 0.006811
    }
  },
  "green-3-20km_ent_fea_mem_np4": {
    "Albany cuda compiler": "Cuda 112",
    "Albany cxx compiler": "GNU 8.3.1",
    "Albany git branch": "master",
    "Albany git commit id": "c6a2c71",
    "Simulation start time": "02:45:06",
    "Trilinos git commit id": "33fab62",
    "case": "green-3-20km_ent_fea_mem",
    "date": 20230227,
    "max host memory": 3114.1875,
    "max kokkos memory": 5996.01,
    "np": 4,
    "passed": true,
    "timers": {
      "Albany Fill: Jacobian:": 9.18401,
      "Albany Fill: Residual:": 1.64838,
      "Albany Jacobian Fill: Evaluate:": 6.0076,
      "Albany Jacobian Fill: Export:": 0.19763,
      "Albany Residual Fill: Evaluate:": 1.33501,
      "Albany Residual Fill: Export:": 0.023012,
      "Albany Total Time:": 17.2691,
      "Albany: Setup Time:": 5.31826,
      "Albany: Total Fill Time:": 10.8339,
      "NOX Total Linear Solve:": 0.794015,
      "NOX Total Preconditioner Construction:": 0.00376692
    }
  },
  "green-3-20km_ent_muk_np4": {
    "Albany cuda compiler": "Cuda 112",
    "Albany cxx compiler": "GNU 8.3.1",
    "Albany git branch": "master",
    "Albany git commit id": "c6a2c71",
    "Simulation start time": "02:45:25",
    "Trilinos git commit id": "33fab62",
    "case": "green-3-20km_ent_muk",
    "date": 20230227,
    "max host memory": 3114.125,
    "max kokkos memory": 6045.1,
    "np": 4,
    "passed": true,
    "timers": {
      "Albany Fill: Jacobian:": 2.63049,
      "Albany Fill: Residual:": 1.16903,
      "Albany Jacobian Fill: Evaluate:": 1.5866,
      "Albany Jacobian Fill: Export:": 0.0729496,
      "Albany Residual Fill: Evaluate:": 0.898388,
      "Albany Residual Fill: Export:": 0.0201956,
      "Albany Total Time:": 24.468,
      "Albany: Setup Time:": 5.43012,
      "Albany: Total Fill Time:": 3.80022,
      "NOX Total Linear Solve:": 8.83474,
      "NOX Total Preconditioner Construction:": 6.10735
    }
  },
  "green-3-20km_pop_np4": {
    "Albany cuda compiler": "Cuda 112",
    "Albany cxx compiler": "GNU 8.3.1",
    "Albany git branch": "master",
    "Albany git commit id": "c6a2c71",
    "Simulation start time": "02:42:18",
    "Trilinos git commit id": "33fab62",
    "case": "green-3-20km_pop",
    "date": 20230227,
    "max host memory": 2390.625,
    "max kokkos memory": 103.556,
    "np": 4,
    "passed": true,
    "timers": {
      "Albany Fill: Residual:": 0.0133089,
      "Albany Residual Fill: Evaluate:": 0.00424483,
      "Albany Residual Fill: Export:": 0.00113808,
      "Albany Total Time:": 6.54003,
      "Albany: Setup Time:": 5.83197,
      "Albany: Total Fill Time:": 0.0137469
    }
  },
  "green-3-20km_vel_fea_1ws_np4": {
    "Albany cuda compiler": "Cuda 112",
    "Albany cxx compiler": "GNU 8.3.1",
    "Albany git branch": "master",
    "Albany git commit id": "c6a2c71",
    "Simulation start time": "02:42:27",
    "Trilinos git commit id": "33fab62",
    "case": "green-3-20km_vel_fea_1ws",
    "date": 20230227,
    "max host memory": 3013.0625,
    "max kokkos memory": 8011.55,
    "np": 4,
    "passed": true,
    "timers": {
      "Albany Fill: Jacobian:": 18.1352,
      "Albany Fill: Residual:": 34.0639,
      "Albany Jacobian Fill: Evaluate:": 17.2396,
      "Albany Jacobian Fill: Export:": 0.42342,
      "Albany Residual Fill: Evaluate:": 33.1462,
      "Albany Residual Fill: Export:": 0.76265,
      "Albany Total Time:": 63.2638,
      "Albany: Setup Time:": 9.6801,
      "Albany: Total Fill Time:": 52.2015,
      "NOX Total Linear Solve:": 0.696621,
      "NOX Total Preconditioner Construction:": 0.00672744
    }
  },
  "green-3-20km_vel_fea_mem_np4": {
    "Albany cuda compiler": "Cuda 112",
    "Albany cxx compiler": "GNU 8.3.1",
    "Albany git branch": "master",
    "Albany git commit id": "c6a2c71",
    "Simulation start time": "02:43:32",
    "Trilinos git commit id": "33fab62",
    "case": "green-3-20km_vel_fea_mem",
    "date": 20230227,
    "max host memory": 3013.1875,
    "max kokkos memory": 8011.55,
    "np": 4,
    "passed": true,
    "timers": {
      "Albany Fill: Jacobian:": 7.88229,
      "Albany Fill: Residual:": 1.51937,
      "Albany Jacobian Fill: Evaluate:": 7.18849,
      "Albany Jacobian Fill: Export:": 0.255944,
      "Albany Residual Fill: Evaluate:": 1.3367,
      "Albany Residual Fill: Export:": 0.0350339,
      "Albany Total Time:": 19.9947,
      "Albany: Setup Time:": 9.57115,
      "Albany: Total Fill Time:": 9.4028,
      "NOX Total Linear Solve:": 0.675934,
      "NOX Total Preconditioner Construction:": 0.00332351
    }
  },
  "green-3-20km_vel_muk_np4": {
    "Albany cuda compiler": "Cuda 112",
    "Albany cxx compiler": "GNU 8.3.1",
    "Albany git branch": "master",
    "Albany git commit id": "c6a2c71",
    "Simulation start time": "02:43:54",
    "Trilinos git commit id": "33fab62",
    "case": "green-3-20km_vel_muk",
    "date": 20230227,
    "max host memory": 3013.25,
    "max kokkos memory": 8063.55,
    "np": 4,
    "passed": true,
    "timers": {
      "Albany Fill: Jacobian:": 1.6949,
      "Albany Fill: Residual:": 0.803676,
      "Albany Jacobian Fill: Evaluate:": 1.22677,
      "Albany Jacobian Fill: Export:": 0.054158,
      "Albany Residual Fill: Evaluate:": 0.629827,
      "Albany Residual Fill: Export:": 0.0182957,
      "Albany Total Time:": 25.4077,
      "Albany: Setup Time:": 9.94593,
      "Albany: Total Fill Time:": 2.49894,
      "NOX Total Linear Solve:": 6.00272,
      "NOX Total Preconditioner Construction:": 6.63853
    }
  },
  "humboldt-1-10km_cop_fea_np4": {
    "Albany cuda compiler": "Cuda 112",
    "Albany cxx compiler": "GNU 8.3.1",
    "Albany git branch": "master",
    "Albany git commit id": "c6a2c71",
    "Simulation start time": "02:45:56",
    "Trilinos git commit id": "33fab62",
    "case": "humboldt-1-10km_cop_fea",
    "date": 20230227,
    "max host memory": 1939.0625,
    "max kokkos memory": 7212.8,
    "np": 4,
    "passed": true,
    "timers": {
      "Albany Fill: Jacobian:": 4.3642,
      "Albany Fill: Residual:": 0.365857,
      "Albany Jacobian Fill: Evaluate:": 3.32706,
      "Albany Jacobian Fill: Export:": 0.0705131,
      "Albany Residual Fill: Evaluate:": 0.24298,
      "Albany Residual Fill: Export:": 0.00763791,
      "Albany Total Time:": 12.9909,
      "Albany: Setup Time:": 7.51568,
      "Albany: Total Fill Time:": 4.73029,
      "NOX Total Linear Solve:": 0.520137,
      "NOX Total Preconditioner Construction:": 0.00120047
    }
  },
  "humboldt-1-10km_pop_np4": {
    "Albany cuda compiler": "Cuda 112",
    "Albany cxx compiler": "GNU 8.3.1",
    "Albany git branch": "master",
    "Albany git commit id": "c6a2c71",
    "Simulation start time": "02:45:52",
    "Trilinos git commit id": "33fab62",
    "case": "humboldt-1-10km_pop",
    "date": 20230227,
    "max host memory": 1453.375,
    "max kokkos memory": 28.298,
    "np": 4,
    "passed": true,
    "timers": {
      "Albany Fill: Residual:": 0.00859118,
      "Albany Residual Fill: Evaluate:": 0.00196908,
      "Albany Residual Fill: Export:": 0.000277822,
      "Albany Total Time:": 2.18266,
      "Albany: Setup Time:": 1.75809,
      "Albany: Total Fill Time:": 0.00908213
    }
  }
}